{
  "users": [
    {
      "id": "5c1c37f6-3ee0-4c07-9c8f-5864f74e627d",
      "username": "johnsmith",
      "password": "P@ssw0rd"
    },
    {
      "id": "84c6673c-6fd6-4184-9193-6111f58c70f7",
      "username": "janedoe",
      "password": "Secret123"
    },
    {
      "id": "72e6876e-5684-4d20-a3ea-ae8482b7e635",
      "username": "mikejones",
      "password": "Summer21"
    },
    {
      "id": "b418df60-825b-41e9-8fe9-293bb61fd4e7",
      "username": "emilybrown",
      "password": "Hello123"
    },
    {
      "id": "c7a3bdf9-4c7e-428a-b0a9-9cb4a244a746",
      "username": "davidwilson",
      "password": "Welcome!"
    },
    {
      "id": "efdd09b1-46b3-4f52-8df3-35675a5c889a",
      "username": "laurajones",
      "password": "Pa$$word1"
    },
    {
      "id": "6a2c3d3d-0d13-47ed-a618-ebd32f7df4c0",
      "username": "chrissmith",
      "password": "Autumn2023"
    },
    {
      "id": "7be5b8b2-299a-4ae5-8ef7-bd8d50a5400e",
      "username": "alexwilson",
      "password": "Sunshine22"
    },
    {
      "id": "dfb04d92-f833-4da2-9610-b5bb3bb21691",
      "username": "sarahmartin",
      "password": "Rainbow45"
    },
    {
      "id": "ab525e05-4766-4a3f-a222-9e5efb45e541",
      "username": "mattjohnson",
      "password": "Spring2023"
    },
    {
      "id": "9a8e45a1-6525-4173-8166-748d6b843a96",
      "username": "lucybrown",
      "password": "Welcome2023!"
    },
    {
      "id": "e7e7a2cd-9cd2-44b7-9e4a-f125c155365e",
      "username": "amysmith",
      "password": "SunnyDays!"
    },
    {
      "id": "a41e05c9-651e-4353-a03a-e757f50664e4",
      "username": "markdavis",
      "password": "SummerVacation"
    },
    {
      "id": "7a9e1a3c-ecfc-41bf-b3e0-2e35a3f0f097",
      "username": "susanjohnson",
      "password": "Beach2023"
    },
    {
      "id": "8425de6d-9a69-4c8e-8e82-53745af6ac59",
      "username": "bobbywilson",
      "password": "Mountain2023"
    },
    {
      "id": "ae1e78bc-82cf-4b5e-8c21-5f81ecbe7a02",
      "username": "katejones",
      "password": "FallSeason2023"
    },
    {
      "id": "41b98e5e-9c09-4ba9-8cd2-44c0441ff47b",
      "username": "jamiebrown",
      "password": "Winter2023!"
    },
    {
      "id": "4f06f172-768d-4e65-ae06-8e5d5c91d71e",
      "username": "robertsmith",
      "password": "SnowyDays!"
    },
    {
      "id": "f74d76c0-56b6-41c8-90a6-4a78a7d5ef2f",
      "username": "laurendavis",
      "password": "MerryXmas2023"
    },
    {
      "id": "0be2898c-29ae-4f6f-a05b-47c856b68d24",
      "username": "jackwilson",
      "password": "NewYear2023"
    },
    {
      "id": "8deffadd-9076-42e1-833e-33b2a87599d9",
      "username": "tommartin",
      "password": "Resolution2023!"
    },
    {
      "id": "c74fc173-322f-4f87-8d20-90f46d066fe6",
      "username": "racheljones",
      "password": "GymTime2023"
    },
    {
      "id": "0bf4e084-3f47-487f-a8ed-64e3384ac5e0",
      "username": "meganbrown",
      "password": "HealthyLife23"
    },
    {
      "id": "5e4d062b-4650-4a9a-9ef0-3b04f5063d53",
      "username": "kevinwilson",
      "password": "FitLife2023!"
    },
    {
      "id": "63a77b24-6f3f-4a16-a194-e868ea6db0a4",
      "username": "joshmartin",
      "password": "WorkoutTime23"
    },
    {
      "id": "f0f4a6bc-f5cb-4c4a-b8e0-4f97c3dc9e8e",
      "username": "patriciabrown",
      "password": "Active2023"
    },
    {
      "id": "28c119f2-9424-460b-82f1-34ecb12dbfe3",
      "username": "danieljones",
      "password": "Healthy2023!"
    },
    {
      "id": "38f708de-1a0d-459e-9d18-3a0b5e85aa4c",
      "username": "taylorwilson",
      "password": "StayFit2023"
    },
    {
      "id": "f0d5e4c5-600b-43b4-a42f-6f618c541c33",
      "username": "gracemartin",
      "password": "Strong2023!"
    },
    {
      "id": "bf66ab68-f900-4c96-85ad-6a9306ea579e",
      "username": "ethanbrown",
      "password": "FitAndFab23"
    },
    {
      "id": "26ce97dd-165a-4226-9f9b-1f04d4f2510f",
      "username": "peterjones",
      "password": "Health2023!"
    },
    {
      "id": "52df7684-9e29-43a0-bb7e-b44e2f8b8b2b",
      "username": "nataliewilson",
      "password": "Wellness23"
    },
    {
      "id": "228ce9df-71f4-46c4-a4db-d85b46431a65",
      "username": "jessicamartin",
      "password": "BeActive2023"
    },
    {
      "id": "b72bc29f-76f1-475d-87b2-d8e7b5c9c20c",
      "username": "robertjones",
      "password": "GetFit2023!"
    },
    {
      "id": "16f2a573-0bf3-4d3d-80c9-f2e8278d95aa",
      "username": "gracebrown",
      "password": "ActiveLife23"
    },
    {
      "id": "1e929c56-6de2-4f7c-b205-0f9a6a8ae7ea",
      "username": "michaelwilson",
      "password": "StayHealthy23"
    },
    {
      "id": "aa2bf3e6-8f2d-4750-9a77-2d570bb3d8c3",
      "username": "sophiamartin",
      "password": "Wellness2023!"
    },
    {
      "id": "60aefb23-93cd-4a09-95ab-b2bba367eb9b",
      "username": "nathanbrown",
      "password": "HealthyLife23"
    },
    {
      "id": "bcf7546c-62c3-4853-a30b-249057f21bf4",
      "username": "andrewjones",
      "password": "Fitness2023!"
    },
    {
      "id": "92e3f93b-d6de-4a87-a518-01737a20a9a0",
      "username": "zoewilson",
      "password": "Active2023!"
    },
    {
      "id": "4178937c-18f3-4ef6-bb5d-9c942215be06",
      "username": "masonmartin",
      "password": "HealthyLiving23"
    },
    {
      "id": "c3f54a97-6a0f-42a7-a9e6-3da850cb146d",
      "username": "victoriabrown",
      "password": "WellnessLife23"
    },
    {
      "id": "8a9e85c7-13f6-486a-9b15-855f44e1b384",
      "username": "jacobjones",
      "password": "FitAndWell23"
    },
    {
      "id": "e62d8d9e-fab9-4d6a-ae5f-222a617e3783",
      "username": "oliviawilson",
      "password": "HealthyHabits23"
    },
    {
      "id": "6b5f38db-39c7-4f2f-a5e5-b7742d81ad9d",
      "username": "dylanbrown",
      "password": "WellnessJourney23"
    },
    {
      "id": "7d545746-f697-4344-9c5e-88d5509d3df0",
      "username": "chrismartin",
      "password": "HealthIsWealth23"
    },
    {
      "id": "74070cd3-3aa7-4af9-8df5-5c71e3a7bf2b",
      "username": "hannahjones",
      "password": "WellnessMission23"
    },
    {
      "id": "c4bf1d6f-80d7-4a63-9b82-5c27db3f4ae0",
      "username": "brandonwilson",
      "password": "HealthyGoals23"
    },
    {
      "id": "a8da6d9e-6872-46d0-852e-51a5c07cfe62",
      "username": "nataliebrown",
      "password": "WellnessChallenge23"
    },
    {
      "id": "bc1710d6-54be-437b-9f3a-cf351f8f6820",
      "username": "jonathanjones",
      "password": "HealthyChoices23"
    },
    {
      "id": "4385d625-5e0b-44c9-871a-4b6e21bbce07",
      "username": "ashleywilson",
      "password": "WellnessJourney23"
    },
    {
      "id": "8dd7c3db-92d2-4596-9d38-4e1771ee317c",
      "username": "zacharymartin",
      "password": "HealthyLifestyle23"
    },
    {
      "id": "216fdc58-27f4-49dd-9c52-80f3a4c5a36f",
      "username": "adrianbrown",
      "password": "WellnessLife23"
    },
    {
      "id": "3ff453d0-755a-4eb1-8c3c-f1254f6b7482",
      "username": "kaylajones",
      "password": "HealthyLiving2023"
    },
    {
      "id": "b5ff7456-df2b-4f27-9f45-d5e30328f63e",
      "username": "austinwilson",
      "password": "WellnessGoals23"
    },
    {
      "id": "d293b92b-59c1-4b13-a997-5d5f89f217cd",
      "username": "rebeccamartin",
      "password": "HealthyStart23"
    },
    {
      "id": "1c258c23-80c6-4b06-98c0-53f2555a75a3",
      "username": "derekbrown",
      "password": "WellnessJourney2023"
    },
    {
      "id": "c6d2357b-6200-47d1-9f18-5b4edee8e196",
      "username": "kellyjones",
      "password": "HealthyChoices2023"
    },
    {
      "id": "5c52b8c7-88d1-4e4c-9ef8-8ab3b3a13f03",
      "username": "patrickwilson",
      "password": "WellnessAdventure23"
    },
    {
      "id": "b36048dc-84db-45c4-b0ef-24e6b78ec635",
      "username": "bridgetmartin",
      "password": "HealthyLifeJourney23"
    },
    {
      "id": "d5a6bdea-80a0-4926-80cc-3bf7ad8653b7",
      "username": "timothybrown",
      "password": "WellnessResolution23"
    }
  ]
}
